discordbot/__init__.py
discordbot/app.py
discordbot/attendance_check.py
discordbot/attendance_function.py
discordbot/discord_bot_back.py
discordbot/is_all_finished.py
lsiwh37249_discordbot-0.1.0.dist-info/METADATA
lsiwh37249_discordbot-0.1.0.dist-info/WHEEL
lsiwh37249_discordbot-0.1.0.dist-info/top_level.txt
lsiwh37249_discordbot-0.1.0.dist-info/RECORD
