Metadata-Version: 2.4
Name: lsiwh37249_discordbot
Version: 0.1.0
Summary: Default template for PDM package
Author-email: kim <lsiwh37249@gmail.com>
License: MIT
Requires-Python: ==3.11.*
Requires-Dist: requests>=2.32.4
Requires-Dist: discord>=2.3.2
Requires-Dist: pandas>=2.3.1
Requires-Dist: uvicorn>=0.35.0
Requires-Dist: fastapi>=0.116.1
